DECIMER/DECIMER_EfficinetNetV2_Transfomer_Trainer.py
DECIMER/Efficient_Net_encoder.py
DECIMER/Predictor_usingCheckpoints.py
DECIMER/Repack_model.py
DECIMER/Transformer_decoder.py
DECIMER/__init__.py
DECIMER/config.py
DECIMER/decimer.py
DECIMER/utils.py
DECIMER/Utils/Create_TFrecord_From_pickles.py
DECIMER/Utils/Create_image_tokenizer.py
DECIMER/efficientnetv2/effnetv2_configs.py
DECIMER/efficientnetv2/effnetv2_model.py
DECIMER/efficientnetv2/hparams.py
DECIMER/efficientnetv2/utils.py
decimer-2.7.1.dist-info/LICENSE
decimer-2.7.1.dist-info/METADATA
decimer-2.7.1.dist-info/WHEEL
decimer-2.7.1.dist-info/entry_points.txt
decimer-2.7.1.dist-info/top_level.txt
decimer-2.7.1.dist-info/RECORD
