Metadata-Version: 2.1
Name: decimer
Version: 2.7.1
Summary: DECIMER 2.6.0: Deep Learning for Chemical Image Recognition using Efficient-Net V2 + Transformer
Home-page: https://github.com/Kohulan/DECIMER-Image_Transformer
Author: Kohulan Rajan
Author-email: kohulan.rajan@uni-jena.de
Maintainer: Kohulan Rajan, Otto Brinkhaus 
Maintainer-email: kohulan.rajan@uni-jena.de, otto.brinkhaus@uni-jena.de
License: MIT
Classifier: Programming Language :: Python :: 3
Classifier: Programming Language :: Python :: 3.5
Classifier: Programming Language :: Python :: 3.6
Classifier: Programming Language :: Python :: 3.7
Classifier: Programming Language :: Python :: 3.8
Classifier: Programming Language :: Python :: 3.9
Classifier: Programming Language :: Python :: 3.10
Classifier: Programming Language :: Python :: 3 :: Only
Classifier: License :: OSI Approved :: MIT License
Classifier: Operating System :: OS Independent
Requires-Python: >=3.5
License-File: LICENSE
Requires-Dist: tensorflow<=2.15.0,>=2.12.0
Requires-Dist: opencv-python
Requires-Dist: pystow
Requires-Dist: pillow-heif
Requires-Dist: efficientnet
Requires-Dist: selfies
Requires-Dist: pyyaml
